mux/dec7seg.v
module dec7seg(data, LED);
input [3:0] data;
output [6:0] LED;

wire [3:0] data; 
reg [6:0] LED; 

always @(data) begin
  case (data)
    4'd0: LED = 7'b1110111;
    4'd1: LED = 7'b1111100;
    4'd2: LED = 7'b0111001;
    4'd3: LED = 7'b1011110;
    4'd4: LED = 7'b1111001;
    4'd5: LED = 7'b1110001;
    default: LED = 7'b0000000;
	endcase
end
endmodule


module dec7seg_test;
  reg [3:0] data;
  wire [6:0] led;

  dec7seg i0(data, led);

  initial begin
    data = 4'd0;
    #10	data = 4'd1;
    #10	data = 4'd2;
    #10	data = 4'd3;
    #10	data = 4'd4;
    #10	data = 4'd5;
    #10	data = 4'd6;
    #10	data = 4'd7;
    #10	data = 4'd8;
    #10	data = 4'd9;
    #10	data = 4'd10;
    #10	data = 4'd11;
    #10	data = 4'd12;
    #10	data = 4'd13;
    #10	data = 4'd14;
    #10	data = 4'd15;
    #10	$finish;
  end

  initial begin
    $monitor("data=%b, LED=%b", data, led);
    $dumpfile("dec7seg_test.vcd");
    $dumpvars(0, dec7seg_test);
  end
endmodule

dec7seg_test.vcd
$date
	Tue Oct 20 23:54:48 2020
$end
$version
	Icarus Verilog
$end
$timescale
	1s
$end
$scope module dec7seg_test $end
$var wire 7 ! led [6:0] $end
$var reg 4 " data [3:0] $end
$scope module i0 $end
$var wire 4 # data [3:0] $end
$var reg 7 $ LED [6:0] $end
$upscope $end
$upscope $end
$enddefinitions $end
#0
$dumpvars
b1110111 $
b0 #
b0 "
b1110111 !
$end
#10
b1111100 !
b1111100 $
b1 "
b1 #
#20
b111001 !
b111001 $
b10 "
b10 #
#30
b1011110 !
b1011110 $
b11 "
b11 #
#40
b1111001 !
b1111001 $
b100 "
b100 #
#50
b1110001 !
b1110001 $
b101 "
b101 #
#60
b0 !
b0 $
b110 "
b110 #
#70
b111 "
b111 #
#80
b1000 "
b1000 #
#90
b1001 "
b1001 #
#100
b1010 "
b1010 #
#110
b1011 "
b1011 #
#120
b1100 "
b1100 #
#130
b1101 "
b1101 #
#140
b1110 "
b1110 #
#150
b1111 "
b1111 #
