dff_masterslave.v
module dff (D,Clk,Q,Q1); //input,Clock,output
  input D,Clk;
  output Q1,Q; // Q1はmasterからの出力
  wire Qm; // masterからの出力(slaveの入力)
  assign Q1=Qm; // masterからの出力とslaveへの入力をつなぐ
  d_latch d1(D,~Clk,Qm); //master
  d_latch d2(Qm,Clk,Q); //slave
endmodule

module d_latch(EN, D, Q);
  input EN, D;
  output Q;
  reg Q;

  /// EN or Dが変化した時
  always @(EN or D)
    // ENが１ならQにDを設定する
    if (EN)
      Q <= D;
endmodule

module dff_test();
  reg d, clk;
  wire q1, q;

  dff DFF(d, clk, q, q1);

  initial begin
    clk=0; d=1;
    #10 clk=1; d=1;
    #10 clk=0; d=0;
    #10 clk=1; d=0;
    #10 clk=0; d=1;
    #10 clk=1; d=0;
    #10 clk=0; d=0;
    #10 clk=1; d=1;
  end

  initial begin
    $monitor("clk=%d, d=%d, q1=%d, q=%d", clk, d, q1, q);
    $dumpfile("dff.vcd");
    $dumpvars(0, dff_test);
  end  
endmodule

dff.vcd
$date
	Wed Oct 21 09:01:20 2020
$end
$version
	Icarus Verilog
$end
$timescale
	1s
$end
$scope module dff_test $end
$var wire 1 ! q1 $end
$var wire 1 " q $end
$var reg 1 # clk $end
$var reg 1 $ d $end
$scope module DFF $end
$var wire 1 # Clk $end
$var wire 1 $ D $end
$var wire 1 ! Q1 $end
$var wire 1 % Qm $end
$var wire 1 " Q $end
$scope module d1 $end
$var wire 1 & D $end
$var wire 1 $ EN $end
$var reg 1 % Q $end
$upscope $end
$scope module d2 $end
$var wire 1 # D $end
$var wire 1 % EN $end
$var reg 1 " Q $end
$upscope $end
$upscope $end
$upscope $end
$enddefinitions $end
#0
$dumpvars
1&
1%
1$
0#
0"
1!
$end
#10
0!
0%
1"
0&
1#
#20
1&
0$
0#
#30
0&
1#
#40
0"
1!
1%
1&
1$
0#
#50
1"
0&
0$
1#
#60
0"
1&
0#
#70
0!
0%
1"
0&
1$
1#
