dec7seg.v
module dec7seg(data, LED);
input [3:0] data;
output [7:0] LED;

wire [3:0] data;
reg [7:0] LED;

always @(data) begin
  case (data)
    4'd0: LED = 7'b1110111;
    4'd1: LED = 7'b1111100;
    4'd2: LED = 7'b0111001;
    4'd3: LED = 7'b1011110;
    4'd4: LED = 7'b1111001;
    4'd5: LED = 7'b1110001;
    default: LED = 7'b0000000;
	endcase
end
endmodule


module dec7seg_test;

reg [3:0] data;
wire [7:0] led;

dec7seg i0(data, led);

initial begin
	data = 4'd0;
  #10	data = 4'd1;
  #10	data = 4'd2;
  #10	data = 4'd3;
  #10	data = 4'd4;
  #10	data = 4'd5;
  #10	data = 4'd6;
  #10	data = 4'd7;
  #10	data = 4'd8;
  #10	data = 4'd9;
  #10	data = 4'd10;
  #10	$finish;
end

initial begin
	$monitor("data=%d, LED=%d", data, led);
	$dumpfile("dump.vcd");
	$dumpvars(0, dec7seg_test);
end

endmodule

dump.vcd
$date
	Fri Oct  9 17:49:31 2020
$end
$version
	Icarus Verilog
$end
$timescale
	1s
$end
$scope module dec7seg_test $end
$var wire 8 ! led [7:0] $end
$var reg 4 " data [3:0] $end
$scope module i0 $end
$var wire 4 # data [3:0] $end
$var reg 8 $ LED [7:0] $end
$upscope $end
$upscope $end
$enddefinitions $end
#0
$dumpvars
b1110111 $
b0 #
b0 "
b1110111 !
$end
#10
b1111100 !
b1111100 $
b1 "
b1 #
#20
b111001 !
b111001 $
b10 "
b10 #
#30
b1011110 !
b1011110 $
b11 "
b11 #
#40
b1111001 !
b1111001 $
b100 "
b100 #
#50
b1110001 !
b1110001 $
b101 "
b101 #
#60
b0 !
b0 $
b110 "
b110 #
#70
b111 "
b111 #
#80
b1000 "
b1000 #
#90
b1001 "
b1001 #
#100
b1010 "
b1010 #
