adder/halfadder.v
module halfadder(
    input x,
    input y,
    output A,
    output cout
);
    assign cout = x & y;
    assign A = x ^ y;
endmodule // halfadder


`timescale 1ns/1ns
module halfadder_test();
    reg input1;
    reg input2;
    wire out;
    wire carryout;
    halfadder uut(
        .x(input1),
        .y(input2),
        .A(out),
        .cout(carryout)
    );
    initial begin
        input1 = 0;
        input2 = 0;
    end
    initial begin
        forever begin
            #5 input1 = $random;
        end
    end
    initial begin
        forever begin
            #5 input2 = $random;
        end
    end
    initial begin
        #100 $finish();
    end
    initial begin
        forever begin
            #5 input2 = $random;
        end
    end
    initial begin
        #100 $finish();
    end
    initial begin
        $monitor("time=%2d, IN1=%1b, IN2=%1b, CarryOut=%1b, OUT=%1b", $time, input1, input2, carryout, out);
        $dumpfile("halfadder.vcd");
        $dumpvars(0, halfadder_test);
    end
endmodule

halfadder.vcd
$date
	Fri Oct 16 11:20:46 2020
$end
$version
	Icarus Verilog
$end
$timescale
	1ns
$end
$scope module halfadder_test $end
$var wire 1 ! out $end
$var wire 1 " carryout $end
$var reg 1 # input1 $end
$var reg 1 $ input2 $end
$scope module uut $end
$var wire 1 ! A $end
$var wire 1 " cout $end
$var wire 1 # x $end
$var wire 1 $ y $end
$upscope $end
$upscope $end
$enddefinitions $end
#0
$dumpvars
0$
0#
0"
0!
$end
#5
1!
1$
#10
1"
0!
1#
#15
1$
#20
1$
#25
1$
#30
0"
0$
0#
#35
1!
0$
1#
#45
0!
0$
0#
#50
1"
1$
1#
#55
0"
1!
0$
#60
1$
0#
#70
1"
0!
1#
#75
0"
1!
1$
0#
#80
0$
1#
#85
0!
0#
#90
0$
#95
1!
1$
