jkff.v
module JKFF (J, K, CLK, Q, QB);
	input J, K, CLK;
	output Q, QB;
	reg Q;	
	
	assign QB = ~Q;	
	
	always@(posedge CLK) begin	
		if(J==1) begin
			if(K==1) begin
				Q <= ~Q;	
			end else begin
				Q <= 1;		
			end
		end else begin
			if(K==1) begin
				Q <= 0;		
			end
		end
	end
endmodule

`timescale 10ps / 10ps

module TESTBENCH;
	reg J, K, CLK;
	wire Q, QB;
	
	JKFF CUT(.J(J), .K(K), .CLK(CLK), .Q(Q), .QB(QB));
	
	initial begin
		$dumpfile("JKFF.vcd");
		$dumpvars(1, TESTBENCH);
		
		CLK <= 0;
		J <= 0; K <= 0; #10 CLK <= 1; #50 CLK <= 0; #40 // 保持
		J <= 1; K <= 0; #10 CLK <= 1; #50 CLK <= 0; #40 // セット
		J <= 0; K <= 0; #10 CLK <= 1; #50 CLK <= 0; #40 // 保持
		J <= 0; K <= 1; #10 CLK <= 1; #50 CLK <= 0; #40 // リセット	
		J <= 0; K <= 0; #10 CLK <= 1; #50 CLK <= 0; #40 // 保持
		J <= 1; K <= 1; #10 CLK <= 1; #50 CLK <= 0; #50 // 反転
                                    CLK <= 1; #50 CLK <= 0; #50 // 反転
                                    CLK <= 1; #50 CLK <= 0; #50 // 反転
                    /* 通常、JK値と クロックは同時に変化させない */
		$finish;
	end
endmodule

JKFF.vcd
$date
	Wed Oct 14 00:05:16 2020
$end
$version
	Icarus Verilog
$end
$timescale
	10ps
$end
$scope module TESTBENCH $end
$var wire 1 ! QB $end
$var wire 1 " Q $end
$var reg 1 # CLK $end
$var reg 1 $ J $end
$var reg 1 % K $end
$upscope $end
$enddefinitions $end
#0
$dumpvars
0%
0$
0#
x"
x!
$end
#10
1#
#60
0#
#100
1$
#110
0!
1"
1#
#160
0#
#200
0$
#210
1#
#260
0#
#300
1%
#310
1!
0"
1#
#360
0#
#400
0%
#410
1#
#460
0#
#500
1%
1$
#510
0!
1"
1#
#560
0#
#610
1!
0"
1#
#660
0#
#710
0!
1"
1#
